pybgpkit_parser-0.6.2.dist-info/METADATA
pybgpkit_parser-0.6.2.dist-info/WHEEL
pybgpkit_parser/__init__.py
pybgpkit_parser/pybgpkit_parser.cpython-313-darwin.so
pybgpkit_parser-0.6.2.dist-info/RECORD
