Metadata-Version: 2.1
Name: pybgpkit-parser
Version: 0.6.2
Summary: BGPKIT Parser Python Binding
Keywords: bgp,mrt,parser
Author: Mingwei Zhang <mingwei@bgpkit.com>
Author-email: Mingwei Zhang <mingwei@bgpkit.com>
License: MIT
Project-URL: Source Code, https://github.com/bgpkit/bgpkit-parser-py
